openweatheronecallapi/__init__.py
openweatheronecallapi/api_helper.py
openweatheronecallapi/configuration.py
openweatheronecallapi/openweatheronecallapi_client.py
openweatheronecallapi/controllers/__init__.py
openweatheronecallapi/controllers/base_controller.py
openweatheronecallapi/controllers/current.py
openweatheronecallapi/exceptions/__init__.py
openweatheronecallapi/exceptions/api_exception.py
openweatheronecallapi/http/__init__.py
openweatheronecallapi/http/http_call_back.py
openweatheronecallapi/http/http_method_enum.py
openweatheronecallapi/http/http_request.py
openweatheronecallapi/http/http_response.py
openweatheronecallapi/http/auth/__init__.py
openweatheronecallapi/http/auth/custom_query_authentication.py
openweatheronecallapi/models/__init__.py
openweatheronecallapi/models/alert.py
openweatheronecallapi/models/current.py
openweatheronecallapi/models/current_weather.py
openweatheronecallapi/models/daily.py
openweatheronecallapi/models/daily_rain.py
openweatheronecallapi/models/daily_snow.py
openweatheronecallapi/models/daily_weather.py
openweatheronecallapi/models/feels_like.py
openweatheronecallapi/models/hourly.py
openweatheronecallapi/models/hourly_rain.py
openweatheronecallapi/models/hourly_snow.py
openweatheronecallapi/models/hourly_weather.py
openweatheronecallapi/models/lang_enum.py
openweatheronecallapi/models/minutely.py
openweatheronecallapi/models/temp.py
openweatheronecallapi/models/units_enum.py
openweatheronecallapi/models/weather_info.py
openweatheronecallapi/utilities/__init__.py
openweatheronecallapi/utilities/file_wrapper.py
open_weather_one_call_sdk-1.0.1.dist-info/LICENSE
open_weather_one_call_sdk-1.0.1.dist-info/METADATA
open_weather_one_call_sdk-1.0.1.dist-info/WHEEL
open_weather_one_call_sdk-1.0.1.dist-info/top_level.txt
open_weather_one_call_sdk-1.0.1.dist-info/RECORD
