Metadata-Version: 2.1
Name: open-weather-one-call-sdk
Version: 1.0.1
Summary: SDK for OneWeather API built by APIMatic
Author-email: Sid Maestre <sid.maestre@apimatic.io>
Project-URL: Documentation, https://openweather-onecall.apimatic.dev/v/3_0_1#/http/step-by-step-tutorial
Requires-Python: >=3.7
License-File: LICENSE
Requires-Dist: apimatic-core ~=0.2.0
Requires-Dist: apimatic-core-interfaces ~=0.1.0
Requires-Dist: apimatic-requests-client-adapter ~=0.1.0
Requires-Dist: python-dateutil ~=2.8.1
Requires-Dist: enum34 >=1.1.10,~=1.1
Provides-Extra: testutils
Requires-Dist: pytest >=7.2.2 ; extra == 'testutils'
